[
  {
    "pic_id": "384381",
    "pic_url": "http://scoot.net/gallery/pic.html?pic=384381&b=2009/08/rattlemybones/Josh/tinyindex.html",
    "photographer": "Josh",
    "date_rally": "2009-08",
    "date_exif": null,
    "date_canonical": null,
    "date_source": "rally_slug"
  },
  {
    "pic_id": "384382",
    "pic_url": "http://scoot.net/gallery/pic.html?pic=384382&b=2009/08/rattlemybones/Josh/tinyindex.html",
    "photographer": "Josh",
    "date_rally": "2009-08",
    "date_exif": null,
    "date_canonical": null,
    "date_source": "rally_slug"
  },
  {
    "pic_id": "384383",
    "pic_url": "http://scoot.net/gallery/pic.html?pic=384383&b=2009/08/rattlemybones/Josh/tinyindex.html",
    "photographer": "Josh",
    "date_rally": "2009-08",
    "date_exif": null,
    "date_canonical": null,
    "date_source": "rally_slug"
  },
  {
    "pic_id": "384384",
    "pic_url": "http://scoot.net/gallery/pic.html?pic=384384&b=2009/08/rattlemybones/Josh/tinyindex.html",
    "photographer": "Josh",
    "date_rally": "2009-08",
    "date_exif": null,
    "date_canonical": null,
    "date_source": "rally_slug"
  },
  {
    "pic_id": "384385",
    "pic_url": "http://scoot.net/gallery/pic.html?pic=384385&b=2009/08/rattlemybones/Josh/tinyindex.html",
    "photographer": "Josh",
    "date_rally": "2009-08",
    "date_exif": null,
    "date_canonical": null,
    "date_source": "rally_slug"
  },
  {
    "pic_id": "384386",
    "pic_url": "http://scoot.net/gallery/pic.html?pic=384386&b=2009/08/rattlemybones/Josh/tinyindex.html",
    "photographer": "Josh",
    "date_rally": "2009-08",
    "date_exif": null,
    "date_canonical": null,
    "date_source": "rally_slug"
  },
  {
    "pic_id": "384387",
    "pic_url": "http://scoot.net/gallery/pic.html?pic=384387&b=2009/08/rattlemybones/Josh/tinyindex.html",
    "photographer": "Josh",
    "date_rally": "2009-08",
    "date_exif": null,
    "date_canonical": null,
    "date_source": "rally_slug"
  },
  {
    "pic_id": "384388",
    "pic_url": "http://scoot.net/gallery/pic.html?pic=384388&b=2009/08/rattlemybones/Josh/tinyindex.html",
    "photographer": "Josh",
    "date_rally": "2009-08",
    "date_exif": null,
    "date_canonical": null,
    "date_source": "rally_slug"
  },
  {
    "pic_id": "384389",
    "pic_url": "http://scoot.net/gallery/pic.html?pic=384389&b=2009/08/rattlemybones/Josh/tinyindex.html",
    "photographer": "Josh",
    "date_rally": "2009-08",
    "date_exif": null,
    "date_canonical": null,
    "date_source": "rally_slug"
  },
  {
    "pic_id": "384390",
    "pic_url": "http://scoot.net/gallery/pic.html?pic=384390&b=2009/08/rattlemybones/Josh/tinyindex.html",
    "photographer": "Josh",
    "date_rally": "2009-08",
    "date_exif": null,
    "date_canonical": null,
    "date_source": "rally_slug"
  },
  {
    "pic_id": "384391",
    "pic_url": "http://scoot.net/gallery/pic.html?pic=384391&b=2009/08/rattlemybones/Josh/tinyindex.html",
    "photographer": "Josh",
    "date_rally": "2009-08",
    "date_exif": null,
    "date_canonical": null,
    "date_source": "rally_slug"
  },
  {
    "pic_id": "384392",
    "pic_url": "http://scoot.net/gallery/pic.html?pic=384392&b=2009/08/rattlemybones/Josh/tinyindex.html",
    "photographer": "Josh",
    "date_rally": "2009-08",
    "date_exif": null,
    "date_canonical": null,
    "date_source": "rally_slug"
  },
  {
    "pic_id": "384393",
    "pic_url": "http://scoot.net/gallery/pic.html?pic=384393&b=2009/08/rattlemybones/Josh/tinyindex.html",
    "photographer": "Josh",
    "date_rally": "2009-08",
    "date_exif": null,
    "date_canonical": null,
    "date_source": "rally_slug"
  },
  {
    "pic_id": "391495",
    "pic_url": "http://scoot.net/gallery/pic.html?pic=391495&b=2009/08/rattlemybones/Howard/tinyindex.html",
    "photographer": "Howard",
    "date_rally": "2009-08",
    "date_exif": null,
    "date_canonical": null,
    "date_source": "rally_slug"
  },
  {
    "pic_id": "391496",
    "pic_url": "http://scoot.net/gallery/pic.html?pic=391496&b=2009/08/rattlemybones/Howard/tinyindex.html",
    "photographer": "Howard",
    "date_rally": "2009-08",
    "date_exif": null,
    "date_canonical": null,
    "date_source": "rally_slug"
  },
  {
    "pic_id": "391497",
    "pic_url": "http://scoot.net/gallery/pic.html?pic=391497&b=2009/08/rattlemybones/Howard/tinyindex.html",
    "photographer": "Howard",
    "date_rally": "2009-08",
    "date_exif": null,
    "date_canonical": null,
    "date_source": "rally_slug"
  },
  {
    "pic_id": "391498",
    "pic_url": "http://scoot.net/gallery/pic.html?pic=391498&b=2009/08/rattlemybones/Howard/tinyindex.html",
    "photographer": "Howard",
    "date_rally": "2009-08",
    "date_exif": null,
    "date_canonical": null,
    "date_source": "rally_slug"
  },
  {
    "pic_id": "391499",
    "pic_url": "http://scoot.net/gallery/pic.html?pic=391499&b=2009/08/rattlemybones/Howard/tinyindex.html",
    "photographer": "Howard",
    "date_rally": "2009-08",
    "date_exif": null,
    "date_canonical": null,
    "date_source": "rally_slug"
  },
  {
    "pic_id": "391500",
    "pic_url": "http://scoot.net/gallery/pic.html?pic=391500&b=2009/08/rattlemybones/Howard/tinyindex.html",
    "photographer": "Howard",
    "date_rally": "2009-08",
    "date_exif": null,
    "date_canonical": null,
    "date_source": "rally_slug"
  },
  {
    "pic_id": "391501",
    "pic_url": "http://scoot.net/gallery/pic.html?pic=391501&b=2009/08/rattlemybones/Howard/tinyindex.html",
    "photographer": "Howard",
    "date_rally": "2009-08",
    "date_exif": null,
    "date_canonical": null,
    "date_source": "rally_slug"
  },
  {
    "pic_id": "391502",
    "pic_url": "http://scoot.net/gallery/pic.html?pic=391502&b=2009/08/rattlemybones/Howard/tinyindex.html",
    "photographer": "Howard",
    "date_rally": "2009-08",
    "date_exif": null,
    "date_canonical": null,
    "date_source": "rally_slug"
  },
  {
    "pic_id": "391503",
    "pic_url": "http://scoot.net/gallery/pic.html?pic=391503&b=2009/08/rattlemybones/Howard/tinyindex.html",
    "photographer": "Howard",
    "date_rally": "2009-08",
    "date_exif": null,
    "date_canonical": null,
    "date_source": "rally_slug"
  },
  {
    "pic_id": "391504",
    "pic_url": "http://scoot.net/gallery/pic.html?pic=391504&b=2009/08/rattlemybones/Howard/tinyindex.html",
    "photographer": "Howard",
    "date_rally": "2009-08",
    "date_exif": null,
    "date_canonical": null,
    "date_source": "rally_slug"
  },
  {
    "pic_id": "391505",
    "pic_url": "http://scoot.net/gallery/pic.html?pic=391505&b=2009/08/rattlemybones/Howard/tinyindex.html",
    "photographer": "Howard",
    "date_rally": "2009-08",
    "date_exif": null,
    "date_canonical": null,
    "date_source": "rally_slug"
  },
  {
    "pic_id": "391506",
    "pic_url": "http://scoot.net/gallery/pic.html?pic=391506&b=2009/08/rattlemybones/Howard/tinyindex.html",
    "photographer": "Howard",
    "date_rally": "2009-08",
    "date_exif": null,
    "date_canonical": null,
    "date_source": "rally_slug"
  },
  {
    "pic_id": "391507",
    "pic_url": "http://scoot.net/gallery/pic.html?pic=391507&b=2009/08/rattlemybones/Howard/tinyindex.html",
    "photographer": "Howard",
    "date_rally": "2009-08",
    "date_exif": null,
    "date_canonical": null,
    "date_source": "rally_slug"
  },
  {
    "pic_id": "391508",
    "pic_url": "http://scoot.net/gallery/pic.html?pic=391508&b=2009/08/rattlemybones/Howard/tinyindex.html",
    "photographer": "Howard",
    "date_rally": "2009-08",
    "date_exif": null,
    "date_canonical": null,
    "date_source": "rally_slug"
  },
  {
    "pic_id": "391509",
    "pic_url": "http://scoot.net/gallery/pic.html?pic=391509&b=2009/08/rattlemybones/Howard/tinyindex.html",
    "photographer": "Howard",
    "date_rally": "2009-08",
    "date_exif": null,
    "date_canonical": null,
    "date_source": "rally_slug"
  },
  {
    "pic_id": "391510",
    "pic_url": "http://scoot.net/gallery/pic.html?pic=391510&b=2009/08/rattlemybones/Howard/tinyindex.html",
    "photographer": "Howard",
    "date_rally": "2009-08",
    "date_exif": null,
    "date_canonical": null,
    "date_source": "rally_slug"
  },
  {
    "pic_id": "391511",
    "pic_url": "http://scoot.net/gallery/pic.html?pic=391511&b=2009/08/rattlemybones/Howard/tinyindex.html",
    "photographer": "Howard",
    "date_rally": "2009-08",
    "date_exif": null,
    "date_canonical": null,
    "date_source": "rally_slug"
  },
  {
    "pic_id": "391512",
    "pic_url": "http://scoot.net/gallery/pic.html?pic=391512&b=2009/08/rattlemybones/Howard/tinyindex.html",
    "photographer": "Howard",
    "date_rally": "2009-08",
    "date_exif": null,
    "date_canonical": null,
    "date_source": "rally_slug"
  },
  {
    "pic_id": "391513",
    "pic_url": "http://scoot.net/gallery/pic.html?pic=391513&b=2009/08/rattlemybones/Howard/tinyindex.html",
    "photographer": "Howard",
    "date_rally": "2009-08",
    "date_exif": null,
    "date_canonical": null,
    "date_source": "rally_slug"
  },
  {
    "pic_id": "391514",
    "pic_url": "http://scoot.net/gallery/pic.html?pic=391514&b=2009/08/rattlemybones/Howard/tinyindex.html",
    "photographer": "Howard",
    "date_rally": "2009-08",
    "date_exif": null,
    "date_canonical": null,
    "date_source": "rally_slug"
  },
  {
    "pic_id": "391515",
    "pic_url": "http://scoot.net/gallery/pic.html?pic=391515&b=2009/08/rattlemybones/Howard/tinyindex.html",
    "photographer": "Howard",
    "date_rally": "2009-08",
    "date_exif": null,
    "date_canonical": null,
    "date_source": "rally_slug"
  },
  {
    "pic_id": "391516",
    "pic_url": "http://scoot.net/gallery/pic.html?pic=391516&b=2009/08/rattlemybones/Howard/tinyindex.html",
    "photographer": "Howard",
    "date_rally": "2009-08",
    "date_exif": null,
    "date_canonical": null,
    "date_source": "rally_slug"
  },
  {
    "pic_id": "391517",
    "pic_url": "http://scoot.net/gallery/pic.html?pic=391517&b=2009/08/rattlemybones/Howard/tinyindex.html",
    "photographer": "Howard",
    "date_rally": "2009-08",
    "date_exif": null,
    "date_canonical": null,
    "date_source": "rally_slug"
  },
  {
    "pic_id": "391518",
    "pic_url": "http://scoot.net/gallery/pic.html?pic=391518&b=2009/08/rattlemybones/Howard/tinyindex.html",
    "photographer": "Howard",
    "date_rally": "2009-08",
    "date_exif": null,
    "date_canonical": null,
    "date_source": "rally_slug"
  },
  {
    "pic_id": "391519",
    "pic_url": "http://scoot.net/gallery/pic.html?pic=391519&b=2009/08/rattlemybones/Howard/tinyindex.html",
    "photographer": "Howard",
    "date_rally": "2009-08",
    "date_exif": null,
    "date_canonical": null,
    "date_source": "rally_slug"
  },
  {
    "pic_id": "384359",
    "pic_url": "http://scoot.net/gallery/pic.html?pic=384359&b=2009/08/rattlemybones/John/tinyindex.html",
    "photographer": "John",
    "date_rally": "2009-08",
    "date_exif": null,
    "date_canonical": null,
    "date_source": "rally_slug"
  },
  {
    "pic_id": "384360",
    "pic_url": "http://scoot.net/gallery/pic.html?pic=384360&b=2009/08/rattlemybones/John/tinyindex.html",
    "photographer": "John",
    "date_rally": "2009-08",
    "date_exif": null,
    "date_canonical": null,
    "date_source": "rally_slug"
  },
  {
    "pic_id": "384361",
    "pic_url": "http://scoot.net/gallery/pic.html?pic=384361&b=2009/08/rattlemybones/John/tinyindex.html",
    "photographer": "John",
    "date_rally": "2009-08",
    "date_exif": null,
    "date_canonical": null,
    "date_source": "rally_slug"
  },
  {
    "pic_id": "384362",
    "pic_url": "http://scoot.net/gallery/pic.html?pic=384362&b=2009/08/rattlemybones/John/tinyindex.html",
    "photographer": "John",
    "date_rally": "2009-08",
    "date_exif": null,
    "date_canonical": null,
    "date_source": "rally_slug"
  },
  {
    "pic_id": "384363",
    "pic_url": "http://scoot.net/gallery/pic.html?pic=384363&b=2009/08/rattlemybones/John/tinyindex.html",
    "photographer": "John",
    "date_rally": "2009-08",
    "date_exif": null,
    "date_canonical": null,
    "date_source": "rally_slug"
  },
  {
    "pic_id": "384364",
    "pic_url": "http://scoot.net/gallery/pic.html?pic=384364&b=2009/08/rattlemybones/John/tinyindex.html",
    "photographer": "John",
    "date_rally": "2009-08",
    "date_exif": null,
    "date_canonical": null,
    "date_source": "rally_slug"
  },
  {
    "pic_id": "384365",
    "pic_url": "http://scoot.net/gallery/pic.html?pic=384365&b=2009/08/rattlemybones/John/tinyindex.html",
    "photographer": "John",
    "date_rally": "2009-08",
    "date_exif": null,
    "date_canonical": null,
    "date_source": "rally_slug"
  },
  {
    "pic_id": "384366",
    "pic_url": "http://scoot.net/gallery/pic.html?pic=384366&b=2009/08/rattlemybones/John/tinyindex.html",
    "photographer": "John",
    "date_rally": "2009-08",
    "date_exif": null,
    "date_canonical": null,
    "date_source": "rally_slug"
  },
  {
    "pic_id": "384367",
    "pic_url": "http://scoot.net/gallery/pic.html?pic=384367&b=2009/08/rattlemybones/John/tinyindex.html",
    "photographer": "John",
    "date_rally": "2009-08",
    "date_exif": null,
    "date_canonical": null,
    "date_source": "rally_slug"
  },
  {
    "pic_id": "384368",
    "pic_url": "http://scoot.net/gallery/pic.html?pic=384368&b=2009/08/rattlemybones/John/tinyindex.html",
    "photographer": "John",
    "date_rally": "2009-08",
    "date_exif": null,
    "date_canonical": null,
    "date_source": "rally_slug"
  },
  {
    "pic_id": "384369",
    "pic_url": "http://scoot.net/gallery/pic.html?pic=384369&b=2009/08/rattlemybones/John/tinyindex.html",
    "photographer": "John",
    "date_rally": "2009-08",
    "date_exif": null,
    "date_canonical": null,
    "date_source": "rally_slug"
  },
  {
    "pic_id": "384370",
    "pic_url": "http://scoot.net/gallery/pic.html?pic=384370&b=2009/08/rattlemybones/John/tinyindex.html",
    "photographer": "John",
    "date_rally": "2009-08",
    "date_exif": null,
    "date_canonical": null,
    "date_source": "rally_slug"
  },
  {
    "pic_id": "384371",
    "pic_url": "http://scoot.net/gallery/pic.html?pic=384371&b=2009/08/rattlemybones/John/tinyindex.html",
    "photographer": "John",
    "date_rally": "2009-08",
    "date_exif": null,
    "date_canonical": null,
    "date_source": "rally_slug"
  },
  {
    "pic_id": "384372",
    "pic_url": "http://scoot.net/gallery/pic.html?pic=384372&b=2009/08/rattlemybones/John/tinyindex.html",
    "photographer": "John",
    "date_rally": "2009-08",
    "date_exif": null,
    "date_canonical": null,
    "date_source": "rally_slug"
  },
  {
    "pic_id": "384373",
    "pic_url": "http://scoot.net/gallery/pic.html?pic=384373&b=2009/08/rattlemybones/John/tinyindex.html",
    "photographer": "John",
    "date_rally": "2009-08",
    "date_exif": null,
    "date_canonical": null,
    "date_source": "rally_slug"
  },
  {
    "pic_id": "384374",
    "pic_url": "http://scoot.net/gallery/pic.html?pic=384374&b=2009/08/rattlemybones/John/tinyindex.html",
    "photographer": "John",
    "date_rally": "2009-08",
    "date_exif": null,
    "date_canonical": null,
    "date_source": "rally_slug"
  },
  {
    "pic_id": "384375",
    "pic_url": "http://scoot.net/gallery/pic.html?pic=384375&b=2009/08/rattlemybones/John/tinyindex.html",
    "photographer": "John",
    "date_rally": "2009-08",
    "date_exif": null,
    "date_canonical": null,
    "date_source": "rally_slug"
  },
  {
    "pic_id": "384376",
    "pic_url": "http://scoot.net/gallery/pic.html?pic=384376&b=2009/08/rattlemybones/John/tinyindex.html",
    "photographer": "John",
    "date_rally": "2009-08",
    "date_exif": null,
    "date_canonical": null,
    "date_source": "rally_slug"
  },
  {
    "pic_id": "384377",
    "pic_url": "http://scoot.net/gallery/pic.html?pic=384377&b=2009/08/rattlemybones/John/tinyindex.html",
    "photographer": "John",
    "date_rally": "2009-08",
    "date_exif": null,
    "date_canonical": null,
    "date_source": "rally_slug"
  },
  {
    "pic_id": "384378",
    "pic_url": "http://scoot.net/gallery/pic.html?pic=384378&b=2009/08/rattlemybones/John/tinyindex.html",
    "photographer": "John",
    "date_rally": "2009-08",
    "date_exif": null,
    "date_canonical": null,
    "date_source": "rally_slug"
  },
  {
    "pic_id": "384379",
    "pic_url": "http://scoot.net/gallery/pic.html?pic=384379&b=2009/08/rattlemybones/John/tinyindex.html",
    "photographer": "John",
    "date_rally": "2009-08",
    "date_exif": null,
    "date_canonical": null,
    "date_source": "rally_slug"
  },
  {
    "pic_id": "384380",
    "pic_url": "http://scoot.net/gallery/pic.html?pic=384380&b=2009/08/rattlemybones/John/tinyindex.html",
    "photographer": "John",
    "date_rally": "2009-08",
    "date_exif": null,
    "date_canonical": null,
    "date_source": "rally_slug"
  }
]